moshi/__init__.py
moshi/client.py
moshi/client_gradio.py
moshi/client_utils.py
moshi/py.typed
moshi/run_inference.py
moshi/run_tts.py
moshi/server.py
moshi/conditioners/__init__.py
moshi/conditioners/base.py
moshi/conditioners/tensors.py
moshi/conditioners/text.py
moshi/models/__init__.py
moshi/models/compression.py
moshi/models/lm.py
moshi/models/lm_utils.py
moshi/models/loaders.py
moshi/models/tts.py
moshi/modules/__init__.py
moshi/modules/conv.py
moshi/modules/conv_test.py
moshi/modules/gating.py
moshi/modules/lora.py
moshi/modules/resample.py
moshi/modules/rope.py
moshi/modules/seanet.py
moshi/modules/seanet_test.py
moshi/modules/streaming.py
moshi/modules/transformer.py
moshi/quantization/__init__.py
moshi/quantization/base.py
moshi/quantization/core_vq.py
moshi/quantization/vq.py
moshi/utils/__init__.py
moshi/utils/autocast.py
moshi/utils/compile.py
moshi/utils/quantize.py
moshi/utils/sampling.py
moshi/utils/utils.py
moshi-0.2.12.dist-info/licenses/LICENSE
moshi-0.2.12.dist-info/licenses/LICENSE.audiocraft
moshi-0.2.12.dist-info/METADATA
moshi-0.2.12.dist-info/WHEEL
moshi-0.2.12.dist-info/entry_points.txt
moshi-0.2.12.dist-info/top_level.txt
moshi-0.2.12.dist-info/RECORD
