Metadata-Version: 2.4
Name: moshi
Version: 0.2.12
Summary: Moshi is moshi
Author-email: Laurent Mazaré <laurent@kyutai.org>
Maintainer-email: Laurent Mazaré <laurent@kyutai.org>
License: MIT
Requires-Python: <3.15,>=3.10
License-File: LICENSE
License-File: LICENSE.audiocraft
Requires-Dist: numpy<2.3,>=1.26
Requires-Dist: safetensors<0.8.0,>=0.4.0
Requires-Dist: huggingface-hub<1.0.0,>=0.24
Requires-Dist: bitsandbytes<0.50.0,>=0.45; sys_platform == "linux"
Requires-Dist: einops<0.9,>=0.7
Requires-Dist: sentencepiece<0.3,>=0.2.0
Requires-Dist: sounddevice==0.5
Requires-Dist: sphn<0.3.0,>=0.2.0
Requires-Dist: torch<2.10,>=2.2.0
Requires-Dist: aiohttp<3.12,>=3.10.5
Requires-Dist: tqdm>=4.48
Provides-Extra: dev
Requires-Dist: pyright; extra == "dev"
Requires-Dist: pytest; extra == "dev"
Requires-Dist: flake8; extra == "dev"
Requires-Dist: pre-commit; extra == "dev"
Requires-Dist: gradio-webrtc>=0.0.18; extra == "dev"
Dynamic: license-file
